pytannic/__init__.py
pytannic/client.py
pytannic/header.py
pytannic/torch/__init__.py
pytannic/torch/modules.py
pytannic/torch/parameters.py
pytannic/torch/tensors.py
pytannic/torch/types.py
pytannic-0.1.3.dist-info/LICENSE
pytannic-0.1.3.dist-info/METADATA
pytannic-0.1.3.dist-info/WHEEL
pytannic-0.1.3.dist-info/RECORD
