Metadata-Version: 2.3
Name: pytannic
Version: 0.1.3
Summary: Python bindings for the Tannic framework
License: Apache-2.0
Author: entropy-flux
Author-email: eric.hermosis@gmail.com
Requires-Python: >=3.12,<3.14
Classifier: License :: OSI Approved :: Apache Software License
Classifier: Programming Language :: Python :: 3
Classifier: Programming Language :: Python :: 3.12
Classifier: Programming Language :: Python :: 3.13
